Semester_3/DSDL/lab2/q1a.v
module q1a(a, b, c, d, f);
	input a, b, c, d;
	output f;
	assign f = ((~c&~d&b)|(b&~a)|(c&d)|(~b&c));
endmodule

Semester_3/DSDL/lab2/q1a_tb.v
`timescale 1ns/1ns
`include "q1a.v"

module q1a_tb();
reg a,b,c,d;
wire f;

q1a q1a(a,b,c,d,f);
initial begin

	$dumpfile("q1a_tb.vcd");
	$dumpvars(0,q1a_tb);
	
	a=0;b=0;c=0;d=0;
	#10;
	
	a=0;b=0;c=0;d=1;
	#10;
	
	a=0;b=0;c=1;d=0;
	#10;
	
	a=0;b=0;c=1;d=1;
	#10;
	
	a=0;b=1;c=0;d=0;
	#10;
	
	a=0;b=1;c=0;d=1;
	#10;
	
	a=0;b=1;c=1;d=0;
	#10;
	
	a=0;b=1;c=1;d=1;
	#10;
	
	a=1;b=0;c=0;d=0;
	#10;
	
	a=1;b=0;c=0;d=1;
	#10;
	
	a=1;b=0;c=1;d=0;
	#10;
	
	a=1;b=0;c=1;d=1;
	#10;
	
	a=1;b=1;c=0;d=0;
	#10;
	
	a=1;b=1;c=0;d=1;
	#10;
	
	a=1;b=1;c=1;d=0;
	#10;
	
	a=1;b=1;c=1;d=1;
	#10;
	
	$display("Test complete");
	
end

endmodule

Semester_3/DSDL/lab2/q1a_tb.vcd
$date
	Thu Sep  1 09:07:31 2022
$end
$version
	Icarus Verilog
$end
$timescale
	1ns
$end
$scope module q1a_tb $end
$var wire 1 ! f $end
$var reg 1 " a $end
$var reg 1 # b $end
$var reg 1 $ c $end
$var reg 1 % d $end
$scope module q1a $end
$var wire 1 " a $end
$var wire 1 # b $end
$var wire 1 $ c $end
$var wire 1 % d $end
$var wire 1 ! f $end
$upscope $end
$upscope $end
$enddefinitions $end
#0
$dumpvars
0%
0$
0#
0"
0!
$end
#10
1%
#20
1!
0%
1$
#30
1%
#40
0%
0$
1#
#50
1%
#60
0%
1$
#70
1%
#80
0!
0%
0$
0#
1"
#90
1%
#100
1!
0%
1$
#110
1%
#120
1!
0%
0$
1#
#130
0!
1%
#140
0%
1$
#150
1!
1%
