Semester_3/DSDL/lab9/q3.v
module q3(W, En, f);
	input [2:0]W;
	input En;
	wire en1, en2;
	wire [0:3]f1, f2;
	output f;
	assign en1= ~W[0]&En;
	assign en2= W[0]&En;
	dec2to4 stage0(W[2:1], en1, f1[0:3]);
	dec2to4 stage1(W[2:1], en2, f2[0:3]);
	assign f=(f1[1]|f1[2]|f2[0]|f2[4]);
endmodule

module dec2to4(W, En, Y);
	input [1:0]W;
	input En;
	output [0:3]Y;
	reg [0:3]Y;
	always @(W or En)
	begin
	if(En==0)
		Y=4'b1111;
	else
	begin
	case(W)
		0:Y=4'b0111;
		1:Y=4'b1011;
		2:Y=4'b1101;
		3:Y=4'b1110;
	endcase	
	end
	end
endmodule

Semester_3/DSDL/lab9/q3_tb.v
`timescale 1ns/1ns
`include "q3.v"

module q3_tb();
reg [2:0]W;
reg En;
wire f;
q3 q3(W, En, f);
initial 
begin
	$dumpfile("q3_tb.vcd");
	$dumpvars(0, q3_tb);

	W=3'b000; En=1'b1; #10;
	W=3'b001; En=1'b1; #10;
	W=3'b010; En=1'b1; #10;
	W=3'b011; En=1'b1; #10;
	W=3'b100; En=1'b1; #10;
	W=3'b101; En=1'b1; #10;
	W=3'b110; En=1'b1; #10;
	W=3'b111; En=1'b1; #10;

	$display("test complete");

end 
endmodule

Semester_3/DSDL/lab9/q3_tb.vcd
$date
	Thu Oct 27 09:35:37 2022
$end
$version
	Icarus Verilog
$end
$timescale
	1ns
$end
$scope module q3_tb $end
$var wire 1 ! f $end
$var reg 1 " En $end
$var reg 3 # W [2:0] $end
$scope module q3 $end
$var wire 1 " En $end
$var wire 3 $ W [2:0] $end
$var wire 1 % en1 $end
$var wire 1 & en2 $end
$var wire 1 ! f $end
$var wire 4 ' f2 [0:3] $end
$var wire 4 ( f1 [0:3] $end
$scope module stage0 $end
$var wire 1 % En $end
$var wire 2 ) W [1:0] $end
$var reg 4 * Y [0:3] $end
$upscope $end
$scope module stage1 $end
$var wire 1 & En $end
$var wire 2 + W [1:0] $end
$var reg 4 , Y [0:3] $end
$upscope $end
$upscope $end
$upscope $end
$enddefinitions $end
#0
$dumpvars
b1111 ,
b0 +
b111 *
b0 )
b111 (
b1111 '
0&
1%
b0 $
b0 #
1"
1!
$end
#10
b1111 (
b1111 *
0%
b111 '
b111 ,
1&
b1 #
b1 $
#20
b1011 (
b1011 *
1%
0&
b1111 '
b1111 ,
b1 )
b1 +
b10 #
b10 $
#30
b1111 (
b1111 *
0%
b1011 '
b1011 ,
1&
b11 #
b11 $
#40
b1101 (
b1101 *
1%
0&
b1111 '
b1111 ,
b10 )
b10 +
b100 #
b100 $
#50
b1111 (
b1111 *
0%
b1101 '
b1101 ,
1&
b101 #
b101 $
#60
b1110 (
b1110 *
1%
0&
b1111 '
b1111 ,
b11 )
b11 +
b110 #
b110 $
#70
b1111 (
b1111 *
0%
b1110 '
b1110 ,
1&
b111 #
b111 $
