Semester_3/DSDL/lab9/q4.v
module q4(W, I, En, f);
	input [2:0]W;
	input [0:7]I;
	input En;
	wire [0:7]f1;
	output f;
	dec3to8 stage0(W[2:0], En, f1[0:7]);
	assign f=(I[0]&f1[0])|(I[1]&f1[1])|(I[2]&f1[2])|(I[3]&f1[3])|(I[4]&f1[4])|(I[5]&f1[5])|(I[6]&f1[6])|(I[7]&f1[7]);
endmodule

module dec3to8(W, En, Y);
	input [2:0]W;
	input En;
	output [0:7]Y;
	reg [0:7]Y;
	integer k;
	always @(W or En)
		for(k=0; k<=7; k=k+1)
			if((W==k)&&(En==1))
				Y[k]=1;
			else 
				Y[k]=0;

endmodule

Semester_3/DSDL/lab9/q4_tb.v
`timescale 1ns/1ns
`include "q4.v"

module q4_tb();
reg [2:0]W;
reg [0:7]I;
reg En;
wire f;
q4 q4(W, I, En, f);
initial 
begin
	$dumpfile("q4_tb.vcd");
	$dumpvars(0, q4_tb);

	I=8'b00000111; W=3'b000; En=1'b1; #10;
	I=8'b00000111; W=3'b001; En=1'b1; #10;
	I=8'b00000111; W=3'b010; En=1'b1; #10;
	I=8'b00000111; W=3'b011; En=1'b1; #10;
	I=8'b00000111; W=3'b100; En=1'b1; #10;
	I=8'b00000111; W=3'b101; En=1'b1; #10;
	I=8'b00000111; W=3'b110; En=1'b1; #10;
	I=8'b00000111; W=3'b111; En=1'b1; #10;

	$display("test complete");

end 
endmodule

Semester_3/DSDL/lab9/q4_tb.vcd
$date
	Thu Oct 27 09:52:07 2022
$end
$version
	Icarus Verilog
$end
$timescale
	1ns
$end
$scope module q4_tb $end
$var wire 1 ! f $end
$var reg 1 " En $end
$var reg 8 # I [0:7] $end
$var reg 3 $ W [2:0] $end
$scope module q4 $end
$var wire 1 " En $end
$var wire 8 % I [0:7] $end
$var wire 3 & W [2:0] $end
$var wire 1 ! f $end
$var wire 8 ' f1 [0:7] $end
$scope module stage0 $end
$var wire 1 " En $end
$var wire 3 ( W [2:0] $end
$var reg 8 ) Y [0:7] $end
$var integer 32 * k [31:0] $end
$upscope $end
$upscope $end
$upscope $end
$enddefinitions $end
#0
$dumpvars
b1000 *
b10000000 )
b0 (
b10000000 '
b0 &
b111 %
b0 $
b111 #
1"
0!
$end
#10
b1000000 '
b1000000 )
b1000 *
b1 $
b1 &
b1 (
#20
b100000 '
b100000 )
b1000 *
b10 $
b10 &
b10 (
#30
b10000 '
b10000 )
b1000 *
b11 $
b11 &
b11 (
#40
b1000 '
b1000 )
b1000 *
b100 $
b100 &
b100 (
#50
1!
b100 '
b100 )
b1000 *
b101 $
b101 &
b101 (
#60
b10 '
b10 )
b1000 *
b110 $
b110 &
b110 (
#70
b1 '
b1 )
b1000 *
b111 $
b111 &
b111 (
