Semester_3/DSDL/lab6/q2/q2.v
module q2(w, s, f);
	input [15:0]w;
	input [3:0]s;
	output f;
	wire [3:0]m;
	mux4to1 stage0(w[0], w[1], w[2], w[3], s[0],s[1], m[0]);
	mux4to1 stage1(w[4], w[5], w[6], w[7], s[0], s[1], m[1]);
	mux4to1 stage2(w[8], w[9], w[10], w[11], s[0], s[1], m[2]);
	mux4to1 stage3(w[12], w[13], w[14], w[15], s[0], s[1], m[3]);
	mux4to1 stage4(m[0], m[1], m[2], m[3], s[2], s[3], f);
endmodule

module mux4to1(w0, w1, w2, w3, s0, s1, f);
	input w0, w1, w2, w3;
	input s0, s1;
	output f;
	reg f;
	always @(*)
	begin
	f = s1?(s0?w3:w2):(s0?w1:w0);
	end
endmodule

Semester_3/DSDL/lab6/q2/q2_tb.v
`timescale 1ns/1ns
`include "q2.v"

module q2_tb();
reg [15:0]w;
reg [3:0]s;
wire f;

q2 q2(w, s, f);
initial 
begin
	$dumpfile("q2_tb.vcd");
	$dumpvars(0,q2_tb);

	w=16'b0001110001110001; s=4'b0000;
	#10;
	w=16'b0001110001110001; s=4'b0001;
	#10;
	w=16'b0001110001110001; s=4'b0010;
	#10;
	w=16'b0001110001110001; s=4'b0011;
	#10;
	w=16'b0001110001110001; s=4'b0100;
	#10;
	w=16'b0001110001110001; s=4'b0101;
	#10;
	w=16'b0001110001110001; s=4'b0110;
	#10;
	w=16'b0001110001110001; s=4'b0111;
	#10;
	w=16'b0001110001110001; s=4'b1000;
	#10;
	w=16'b0001110001110001; s=4'b1001;
	#10;
	w=16'b0001110001110001; s=4'b1010;
	#10;
	w=16'b0001110001110001; s=4'b1011;
	#10;
	w=16'b0001110001110001; s=4'b1100;
	#10;
	w=16'b0001110001110001; s=4'b1101;
	#10;
	w=16'b0001110001110001; s=4'b1110;
	#10;
	w=16'b0001110001110001; s=4'b1111;
	#10;

	$display("test complete");
end
endmodule

Semester_3/DSDL/lab6/q2/q2_tb.vcd
$date
	Thu Oct  6 10:33:32 2022
$end
$version
	Icarus Verilog
$end
$timescale
	1ns
$end
$scope module q2_tb $end
$var wire 1 ! f $end
$var reg 4 " s [3:0] $end
$var reg 16 # w [15:0] $end
$scope module q2 $end
$var wire 4 $ s [3:0] $end
$var wire 16 % w [15:0] $end
$var wire 4 & m [3:0] $end
$var wire 1 ! f $end
$scope module stage0 $end
$var wire 1 ' s0 $end
$var wire 1 ( s1 $end
$var wire 1 ) w0 $end
$var wire 1 * w1 $end
$var wire 1 + w2 $end
$var wire 1 , w3 $end
$var reg 1 - f $end
$upscope $end
$scope module stage1 $end
$var wire 1 . s0 $end
$var wire 1 / s1 $end
$var wire 1 0 w0 $end
$var wire 1 1 w1 $end
$var wire 1 2 w2 $end
$var wire 1 3 w3 $end
$var reg 1 4 f $end
$upscope $end
$scope module stage2 $end
$var wire 1 5 s0 $end
$var wire 1 6 s1 $end
$var wire 1 7 w0 $end
$var wire 1 8 w1 $end
$var wire 1 9 w2 $end
$var wire 1 : w3 $end
$var reg 1 ; f $end
$upscope $end
$scope module stage3 $end
$var wire 1 < s0 $end
$var wire 1 = s1 $end
$var wire 1 > w0 $end
$var wire 1 ? w1 $end
$var wire 1 @ w2 $end
$var wire 1 A w3 $end
$var reg 1 B f $end
$upscope $end
$scope module stage4 $end
$var wire 1 C s0 $end
$var wire 1 D s1 $end
$var wire 1 E w0 $end
$var wire 1 F w1 $end
$var wire 1 G w2 $end
$var wire 1 H w3 $end
$var reg 1 ! f $end
$upscope $end
$upscope $end
$upscope $end
$enddefinitions $end
#0
$dumpvars
1H
0G
1F
1E
0D
0C
1B
0A
0@
0?
1>
0=
0<
0;
1:
19
08
07
06
05
14
03
12
11
10
0/
0.
1-
0,
0+
0*
1)
0(
0'
b1011 &
b1110001110001 %
b0 $
b1110001110001 #
b0 "
1!
$end
#10
0!
0E
0H
0-
b10 &
0B
1'
1.
15
1<
b1 "
b1 $
#20
1G
b110 &
1;
0'
1(
0.
1/
05
16
0<
1=
b10 "
b10 $
#30
0F
b100 &
04
1'
1.
15
1<
b11 "
b11 $
#40
1!
1E
1F
0G
1H
1-
14
0;
b1011 &
1B
0'
0(
0.
0/
05
06
0<
0=
1C
b100 "
b100 $
#50
0E
0H
0-
b10 &
0B
1'
1.
15
1<
b101 "
b101 $
#60
1G
b110 &
1;
0'
1(
0.
1/
05
16
0<
1=
b110 "
b110 $
#70
0!
0F
b100 &
04
1'
1.
15
1<
b111 "
b111 $
#80
1E
1F
0G
1H
1-
14
0;
b1011 &
1B
0!
0'
0(
0.
0/
05
06
0<
0=
0C
1D
b1000 "
b1000 $
#90
0E
0H
0-
b10 &
0B
1'
1.
15
1<
b1001 "
b1001 $
#100
1!
1G
b110 &
1;
0'
1(
0.
1/
05
16
0<
1=
b1010 "
b1010 $
#110
0F
b100 &
04
1'
1.
15
1<
b1011 "
b1011 $
#120
1E
1F
0G
1H
1-
14
0;
b1011 &
1B
1!
0'
0(
0.
0/
05
06
0<
0=
1C
b1100 "
b1100 $
#130
0!
0E
0H
0-
b10 &
0B
1'
1.
15
1<
b1101 "
b1101 $
#140
1G
b110 &
1;
0'
1(
0.
1/
05
16
0<
1=
b1110 "
b1110 $
#150
0F
b100 &
04
1'
1.
15
1<
b1111 "
b1111 $
