Semester_3/DSDL/lab3/q2.v
module q2(a, b, c, d, f);
	input a, b, c, d;
	output f;
	nor(g1, d, d);
	nor(g2, c, b);
	nor(g3, b, d);
	nor(g4, c, g1, a);
	nor(g5, g2, g3, g4);
	nor(f, g5, g5);
	
endmodule

Semester_3/DSDL/lab3/q2_tb.v
`timescale 1ns/1ns
`include "q2.v"

module q2_tb();
reg a,b,c,d;
wire f;

q2 q2(a,b,c,d,f);
initial begin

	$dumpfile("q2_tb.vcd");
	$dumpvars(0,q2_tb);
	
	a=0;b=0;c=0;d=0;
	#10;
	
	a=0;b=0;c=0;d=1;
	#10;
	
	a=0;b=0;c=1;d=0;
	#10;
	
	a=0;b=0;c=1;d=1;
	#10;
	
	a=0;b=1;c=0;d=0;
	#10;
	
	a=0;b=1;c=0;d=1;
	#10;
	
	a=0;b=1;c=1;d=0;
	#10;
	
	a=0;b=1;c=1;d=1;
	#10;
	
	a=1;b=0;c=0;d=0;
	#10;
	
	a=1;b=0;c=0;d=1;
	#10;
	
	a=1;b=0;c=1;d=0;
	#10;
	
	a=1;b=0;c=1;d=1;
	#10;
	
	a=1;b=1;c=0;d=0;
	#10;
	
	a=1;b=1;c=0;d=1;
	#10;
	
	a=1;b=1;c=1;d=0;
	#10;
	
	a=1;b=1;c=1;d=1;
	#10;
	
	$display("Test complete");
	
end

endmodule

Semester_3/DSDL/lab3/q2_tb.vcd
$date
	Thu Sep  8 11:23:18 2022
$end
$version
	Icarus Verilog
$end
$timescale
	1ns
$end
$scope module q2_tb $end
$var wire 1 ! f $end
$var reg 1 " a $end
$var reg 1 # b $end
$var reg 1 $ c $end
$var reg 1 % d $end
$scope module q2 $end
$var wire 1 " a $end
$var wire 1 # b $end
$var wire 1 $ c $end
$var wire 1 % d $end
$var wire 1 ! f $end
$var wire 1 & g1 $end
$var wire 1 ' g2 $end
$var wire 1 ( g3 $end
$var wire 1 ) g4 $end
$var wire 1 * g5 $end
$upscope $end
$upscope $end
$enddefinitions $end
#0
$dumpvars
0*
0)
1(
1'
1&
0%
0$
0#
0"
1!
$end
#10
1)
0&
0(
1%
#20
1&
1(
0'
0)
0%
1$
#30
0!
1*
0&
0(
1%
#40
0!
1*
1&
0)
0%
0$
1#
#50
1!
0*
1)
0&
1%
#60
0!
1*
1&
0)
0%
1$
#70
0&
1%
#80
1!
0*
1&
1'
1(
0%
0$
0#
1"
#90
0&
0(
1%
#100
1&
1(
0'
0%
1$
#110
0!
1*
0&
0(
1%
#120
1&
0%
0$
1#
#130
0&
1%
#140
1&
0%
1$
#150
0&
1%
