Semester_3/DSDL/lab4/q1/q1b.v
module q1b(Cin, x, y, s, Cout);
	input Cin, x, y;
	output s, Cout;
	assign s = x^y^Cin;
	assign Cout = (x&y)|(x&Cin)|(y&Cin);
endmodule

Semester_3/DSDL/lab4/q1/q1b_tb.v
`timescale 1ns/1ns
`include "q1b.v"

module q1b_tb();
reg Cin, x, y;
wire s, Cout;
q1b q1b(Cin, x, y, s, Cout);

initial
begin

	$dumpfile("q1b_tb.vcd");
	$dumpvars(0, q1b_tb);
	
	x=0; y=0; Cin=0;
	#10;
	x=0; y=0; Cin=1;
	#10;
	x=0; y=1; Cin=0;
	#10;
	x=0; y=1; Cin=1;
	#10;
	x=1; y=0; Cin=0;
	#10;
	x=1; y=0; Cin=1;
	#10;
	x=1; y=1; Cin=0;
	#10;
	x=1; y=1; Cin=1;
	#10;
	

	
	$display("Test complete");
	
end
endmodule

Semester_3/DSDL/lab4/q1/q1b_tb.vcd
$date
	Thu Sep 15 10:02:13 2022
$end
$version
	Icarus Verilog
$end
$timescale
	1ns
$end
$scope module q1b_tb $end
$var wire 1 ! s $end
$var wire 1 " Cout $end
$var reg 1 # Cin $end
$var reg 1 $ x $end
$var reg 1 % y $end
$scope module q1b $end
$var wire 1 # Cin $end
$var wire 1 " Cout $end
$var wire 1 ! s $end
$var wire 1 $ x $end
$var wire 1 % y $end
$upscope $end
$upscope $end
$enddefinitions $end
#0
$dumpvars
0%
0$
0#
0"
0!
$end
#10
1!
1#
#20
0#
1%
#30
1"
0!
1#
#40
0"
1!
0#
0%
1$
#50
1"
0!
1#
#60
0#
1%
#70
1!
1#
