Semester_3/DSDL/lab4/q1/q1c.v
module q1c(x, y, Cin, s, Cout);
	input x, y, Cin;
	output s, Cout;
	halfadd stage0(x, y, s0, c0);
	halfadd stage1(s0, Cin, s, c1);
	assign Cout = (c0|c1);
endmodule

module halfadd(x, y, s, c);
	input x, y;
	output s, c;
	assign s = x^y;
	assign c = x&y;
endmodule

Semester_3/DSDL/lab4/q1/q1c_tb.v
`timescale 1ns/1ns
`include "q1c.v"

module q1c_tb();
reg x, y, Cin;
wire s, Cout;
q1c q1c(Cin, x, y, s, Cout);

initial
begin

	$dumpfile("q1c_tb.vcd");
	$dumpvars(0, q1c_tb);
	
	x=0; y=0; Cin=0;
	#10;
	x=0; y=0; Cin=1;
	#10;
	x=0; y=1; Cin=0;
	#10;
	x=0; y=1; Cin=1;
	#10;
	x=1; y=0; Cin=0;
	#10;
	x=1; y=0; Cin=1;
	#10;
	x=1; y=1; Cin=0;
	#10;
	x=1; y=1; Cin=1;
	#10;
	
	
	$display("Test complete");
	
end
endmodule

Semester_3/DSDL/lab4/q1/q1c_tb.vcd
$date
	Thu Sep 15 11:02:05 2022
$end
$version
	Icarus Verilog
$end
$timescale
	1ns
$end
$scope module q1c_tb $end
$var wire 1 ! s $end
$var wire 1 " Cout $end
$var reg 1 # Cin $end
$var reg 1 $ x $end
$var reg 1 % y $end
$scope module q1c $end
$var wire 1 % Cin $end
$var wire 1 " Cout $end
$var wire 1 # x $end
$var wire 1 $ y $end
$var wire 1 & s0 $end
$var wire 1 ! s $end
$var wire 1 ' c1 $end
$var wire 1 ( c0 $end
$scope module stage0 $end
$var wire 1 ( c $end
$var wire 1 & s $end
$var wire 1 # x $end
$var wire 1 $ y $end
$upscope $end
$scope module stage1 $end
$var wire 1 ' c $end
$var wire 1 ! s $end
$var wire 1 & x $end
$var wire 1 % y $end
$upscope $end
$upscope $end
$upscope $end
$enddefinitions $end
#0
$dumpvars
0(
0'
0&
0%
0$
0#
0"
0!
$end
#10
1!
1&
1#
#20
0"
0&
1!
0'
0#
1%
#30
1"
0!
1'
1&
1#
#40
0"
1!
0'
0#
0%
1$
#50
0!
1"
0&
1(
1#
#60
1'
1"
1&
0(
0!
0#
1%
#70
1!
0'
0&
1(
1#
