Semester_3/DSDL/lab6/q3/q3.v
module q3(w, s, f);
	input [15:0]w;
	input [3:0]s;
	output f;
	wire[1:0]m;
	mux8to1 stage0(w[7:0], s[2:0], m[0]);
	mux8to1 stage1(w[15:8], s[2:0], m[1]);
	mux2to1 stage2(m[0], m[1], s[3], f);
endmodule

module mux8to1(w, s, f);
	input [7:0]w;
	input [2:0]s;
	output reg f;
	always @(w or s)
		case(s)
		0:f=w[0];
		1:f=w[1];
		2:f=w[2];
		3:f=w[3];
		4:f=w[4];
		5:f=w[5];
		6:f=w[6];
		7:f=w[7];
		endcase
endmodule

module mux2to1(w0, w1, s, f);
	input w0, w1, s;
	output f;
	reg f;
	always @(w0 or w1 or s)
		 f = s?w1:w0;
endmodule

Semester_3/DSDL/lab6/q3/q3_tb.v
`timescale 1ns/1ns
`include "q3.v"

module q3_tb();
reg [15:0]w;
reg [3:0]s;
wire f;

q3 q3(w, s, f);
initial 
begin
	$dumpfile("q3_tb.vcd");
	$dumpvars(0,q3_tb);

	w=16'b0001110001110001; s=4'b0000;
	#10;
	w=16'b0001110001110001; s=4'b0001;
	#10;
	w=16'b0001110001110001; s=4'b0010;
	#10;
	w=16'b0001110001110001; s=4'b0011;
	#10;
	w=16'b0001110001110001; s=4'b0100;
	#10;
	w=16'b0001110001110001; s=4'b0101;
	#10;
	w=16'b0001110001110001; s=4'b0110;
	#10;
	w=16'b0001110001110001; s=4'b0111;
	#10;
	w=16'b0001110001110001; s=4'b1000;
	#10;
	w=16'b0001110001110001; s=4'b1001;
	#10;
	w=16'b0001110001110001; s=4'b1010;
	#10;
	w=16'b0001110001110001; s=4'b1011;
	#10;
	w=16'b0001110001110001; s=4'b1100;
	#10;
	w=16'b0001110001110001; s=4'b1101;
	#10;
	w=16'b0001110001110001; s=4'b1110;
	#10;
	w=16'b0001110001110001; s=4'b1111;
	#10;

	$display("test complete");
end
endmodule

Semester_3/DSDL/lab6/q3/q3_tb.vcd
$date
	Thu Oct  6 10:52:51 2022
$end
$version
	Icarus Verilog
$end
$timescale
	1ns
$end
$scope module q3_tb $end
$var wire 1 ! f $end
$var reg 4 " s [3:0] $end
$var reg 16 # w [15:0] $end
$scope module q3 $end
$var wire 4 $ s [3:0] $end
$var wire 16 % w [15:0] $end
$var wire 2 & m [1:0] $end
$var wire 1 ! f $end
$scope module stage0 $end
$var wire 3 ' s [2:0] $end
$var wire 8 ( w [7:0] $end
$var reg 1 ) f $end
$upscope $end
$scope module stage1 $end
$var wire 3 * s [2:0] $end
$var wire 8 + w [7:0] $end
$var reg 1 , f $end
$upscope $end
$scope module stage2 $end
$var wire 1 - s $end
$var wire 1 . w0 $end
$var wire 1 / w1 $end
$var reg 1 ! f $end
$upscope $end
$upscope $end
$upscope $end
$enddefinitions $end
#0
$dumpvars
0/
1.
0-
0,
b11100 +
b0 *
1)
b1110001 (
b0 '
b1 &
b1110001110001 %
b0 $
b1110001110001 #
b0 "
1!
$end
#10
0!
0.
b0 &
0)
b1 '
b1 *
b1 "
b1 $
#20
1/
b10 &
1,
b10 '
b10 *
b10 "
b10 $
#30
b11 '
b11 *
b11 "
b11 $
#40
1!
1.
b11 &
1)
b100 '
b100 *
b100 "
b100 $
#50
0/
b1 &
0,
b101 '
b101 *
b101 "
b101 $
#60
b110 '
b110 *
b110 "
b110 $
#70
0!
0.
b0 &
0)
b111 '
b111 *
b111 "
b111 $
#80
1.
b1 &
1)
b0 '
b0 *
1-
b1000 "
b1000 $
#90
0.
b0 &
0)
b1 '
b1 *
b1001 "
b1001 $
#100
1!
1/
b10 &
1,
b10 '
b10 *
b1010 "
b1010 $
#110
b11 '
b11 *
b1011 "
b1011 $
#120
1.
b11 &
1)
b100 '
b100 *
b1100 "
b1100 $
#130
0!
0/
b1 &
0,
b101 '
b101 *
b1101 "
b1101 $
#140
b110 '
b110 *
b1110 "
b1110 $
#150
0.
b0 &
0)
b111 '
b111 *
b1111 "
b1111 $
