Semester_3/DSDL/lab6/example/eg1.v
module eg1(w0, w1, s, f);
	input w0, w1, s;
	output f;
	reg f;
	always @(w0 or w1 or s)
		 f = s?w1:w0;
endmodule

Semester_3/DSDL/lab6/example/eg1_tb.v
`timescale 1ns/1ns
`include "eg1.v"

module eg1_tb();
reg w0, w1, s;
eg1 eg1(w0, w1, s, f);
initial 
begin
	$dumpfile("eg1_tb.vcd");
	$dumpvars(0,eg1_tb);

	s=1'b0;w0=1'b0;w1=1'b0;
	#20;
	s=1'b0;w0=1'b0;w1=1'b1;
	#20;
	s=1'b0;w0=1'b1;w1=1'b0;
	#20;
	s=1'b0;w0=1'b1;w1=1'b1;
	#20;
	s=1'b1;w0=1'b0;w1=1'b0;
	#20;
	s=1'b1;w0=1'b0;w1=1'b1;
	#20;
	s=1'b1;w0=1'b1;w1=1'b0;
	#20;
	s=1'b1;w0=1'b1;w1=1'b1;
	#20;
	
	$display("test complete");
end
endmodule

Semester_3/DSDL/lab6/example/eg1_tb.vcd
$date
	Thu Oct  6 09:02:02 2022
$end
$version
	Icarus Verilog
$end
$timescale
	1ns
$end
$scope module eg1_tb $end
$var wire 1 ! f $end
$var reg 1 " s $end
$var reg 1 # w0 $end
$var reg 1 $ w1 $end
$scope module eg1 $end
$var wire 1 " s $end
$var wire 1 # w0 $end
$var wire 1 $ w1 $end
$var reg 1 ! f $end
$upscope $end
$upscope $end
$enddefinitions $end
#0
$dumpvars
0$
0#
0"
0!
$end
#20
1$
#40
1!
0$
1#
#60
1$
#80
0!
0$
0#
1"
#100
1!
1$
#120
0!
0$
1#
#140
1!
1$
