Semester_3/DSDL/lab1/q2a.v
module q2a(a, b, c, d, f, g);
	input a, b, c, d;
	output f, g;
	nand(h, a, b);
	xor(f, h, c, d);
	nor(g, d, c, b);
endmodule

Semester_3/DSDL/lab1/q2a_tb.v
`timescale 1ns/1ns
`include "q2a.v"

module q2a_tb;
reg a,b,c,d;
wire f,g;

q2a q2a(a,b,c,d,f,g);
initial begin

	$dumpfile("q2a_tb.vcd");
	$dumpvars(0,q2a_tb);
	
	a=0;b=0;c=0;d=0;
	#10;
	
	a=0;b=0;c=0;d=1;
	#10;
	
	a=0;b=0;c=1;d=0;
	#10;
	
	a=0;b=0;c=1;d=1;
	#10;
	
	a=0;b=1;c=0;d=0;
	#10;
	
	a=0;b=1;c=0;d=1;
	#10;
	
	a=0;b=1;c=1;d=0;
	#10;
	
	a=0;b=1;c=1;d=1;
	#10;
	
	a=1;b=0;c=0;d=0;
	#10;
	
	a=1;b=0;c=0;d=1;
	#10;
	
	a=1;b=0;c=1;d=0;
	#10;
	
	a=1;b=0;c=1;d=1;
	#10;
	
	a=1;b=1;c=0;d=0;
	#10;
	
	a=1;b=1;c=0;d=1;
	#10;
	
	a=1;b=1;c=1;d=0;
	#10;
	
	a=1;b=1;c=1;d=1;
	#10;
	
	$display("Test complete");
	
end

endmodule

Semester_3/DSDL/lab1/q2a_tb.vcd
$date
	Thu Aug 25 09:56:30 2022
$end
$version
	Icarus Verilog
$end
$timescale
	1ns
$end
$scope module q2a_tb $end
$var wire 1 ! g $end
$var wire 1 " f $end
$var reg 1 # a $end
$var reg 1 $ b $end
$var reg 1 % c $end
$var reg 1 & d $end
$scope module q2a $end
$var wire 1 # a $end
$var wire 1 $ b $end
$var wire 1 % c $end
$var wire 1 & d $end
$var wire 1 " f $end
$var wire 1 ! g $end
$var wire 1 ' h $end
$upscope $end
$upscope $end
$enddefinitions $end
#0
$dumpvars
1'
0&
0%
0$
0#
1"
1!
$end
#10
0"
0!
1&
#20
0&
1%
#30
1"
1&
#40
0&
0%
1$
#50
0"
1&
#60
0&
1%
#70
1"
1&
#80
1!
0&
0%
0$
1#
#90
0"
0!
1&
#100
0&
1%
#110
1"
1&
#120
0"
0'
0&
0%
1$
#130
1"
1&
#140
0&
1%
#150
0"
1&
