Semester_3/DSDL/lab6/q1/q1.v
module q1(w, s0, s1, f);
	input [3:0]w;
	input s0, s1;
	output f;
	wire f1, f2;
	mux2to1 stage0(w[0], w[1], s0, f1);
	mux2to1 stage1(w[2], w[3], s0, f2);
	mux2to1 stage2(f1, f2, s1, f);
endmodule


module mux2to1(w0, w1, s, f);
	input w0, w1, s;
	output f;
	reg f;
	always@(w0 or w1 or s)
	begin
	if(s==0)
		assign f = w0;
	else 
		assign f = w1;
	end
endmodule

Semester_3/DSDL/lab6/q1/q1_tb.v
`timescale 1ns/1ns
`include "q1.v"

module q1_tb();
reg [3:0]w;
reg s0, s1;
wire f;

q1 q1(w, s0, s1, f);
initial 
begin
	$dumpfile("q1_tb.vcd");
	$dumpvars(0,q1_tb);

	w=4'b0011;s0=1'b0;s1=1'b0;
	#10;
	w=4'b0011;s0=1'b0;s1=1'b1;
	#10;
	w=4'b0011;s0=1'b1;s1=1'b0;
	#10;
	w=4'b0011;s0=1'b1;s1=1'b1;
	#10;

	w=4'b1010;s0=1'b0;s1=1'b0;
	#10;
	w=4'b1010;s0=1'b0;s1=1'b1;
	#10;
	w=4'b1010;s0=1'b1;s1=1'b0;
	#10;
	w=4'b1010;s0=1'b1;s1=1'b1;
	#10;

	$display("test complete");
end
endmodule

Semester_3/DSDL/lab6/q1/q1_tb.vcd
$date
	Thu Oct  6 10:06:26 2022
$end
$version
	Icarus Verilog
$end
$timescale
	1ns
$end
$scope module q1_tb $end
$var wire 1 ! f $end
$var reg 1 " s0 $end
$var reg 1 # s1 $end
$var reg 4 $ w [3:0] $end
$scope module q1 $end
$var wire 1 " s0 $end
$var wire 1 # s1 $end
$var wire 4 % w [3:0] $end
$var wire 1 & f2 $end
$var wire 1 ' f1 $end
$var wire 1 ! f $end
$scope module stage0 $end
$var wire 1 " s $end
$var wire 1 ( w0 $end
$var wire 1 ) w1 $end
$var reg 1 ' f $end
$upscope $end
$scope module stage1 $end
$var wire 1 " s $end
$var wire 1 * w0 $end
$var wire 1 + w1 $end
$var reg 1 & f $end
$upscope $end
$scope module stage2 $end
$var wire 1 # s $end
$var wire 1 ' w0 $end
$var wire 1 & w1 $end
$var reg 1 ! f $end
$upscope $end
$upscope $end
$upscope $end
$enddefinitions $end
#0
$dumpvars
0+
0*
1)
1(
1'
0&
b11 %
b11 $
0#
0"
1!
$end
#10
0!
1#
#20
1!
0#
1"
#30
0!
1#
#40
0'
0(
0!
0&
1+
0#
0"
b1010 $
b1010 %
#50
1#
#60
1'
1!
1&
0#
1"
#70
1#
