Semester_3/DSDL/lab8/q2.v
module q2(W, En, Y);
	input [3:0]W;
	input En;
	output [0:15]Y;

	dec3to8 stage0(W[2:0], (~W[3]&En), Y[0:7]);
	dec3to8 stage1(W[2:0], (W[3]&En), Y[8:15]);
endmodule

module dec3to8(W, En, Y);
	input [2:0]W;
	input En;
	output [0:7]Y;
	reg [0:7]Y;
	integer k;
	always @(W or En)
		for(k=0; k<=7; k=k+1)
			if((W==k)&&(En==1))
				Y[k]=1;
			else 
				Y[k]=0;

endmodule

Semester_3/DSDL/lab8/q2_tb.v
`timescale 1ns/1ns
`include "q2.v"

module q2_tb();
reg [3:0]W;
reg En;
wire [0:15]Y;
q2 q2(W, En, Y);
initial 
begin

	$dumpfile("q2_tb.vcd");
	$dumpvars(0, q2_tb);

	W=4'b0000;En=1'b1;#10;
	W=4'b0001;En=1'b1;#10;
	W=4'b0010;En=1'b1;#10;
	W=4'b0011;En=1'b1;#10;
	W=4'b0100;En=1'b1;#10;
	W=4'b0101;En=1'b1;#10;
	W=4'b0110;En=1'b1;#10;
	W=4'b0111;En=1'b1;#10;
	W=4'b1000;En=1'b1;#10;
	W=4'b1001;En=1'b1;#10;
	W=4'b1010;En=1'b1;#10;
	W=4'b1011;En=1'b1;#10;
	W=4'b1100;En=1'b1;#10;
	W=4'b1101;En=1'b1;#10;
	W=4'b1110;En=1'b1;#10;
	W=4'b1111;En=1'b1;#10;

	$display("Test Completed");

end 
endmodule

Semester_3/DSDL/lab8/q2_tb.vcd
$date
	Thu Oct 20 09:55:38 2022
$end
$version
	Icarus Verilog
$end
$timescale
	1ns
$end
$scope module q2_tb $end
$var wire 16 ! Y [0:15] $end
$var reg 1 " En $end
$var reg 4 # W [3:0] $end
$scope module q2 $end
$var wire 1 " En $end
$var wire 4 $ W [3:0] $end
$var wire 16 % Y [0:15] $end
$scope module stage0 $end
$var wire 1 & En $end
$var wire 3 ' W [2:0] $end
$var reg 8 ( Y [0:7] $end
$var integer 32 ) k [31:0] $end
$upscope $end
$scope module stage1 $end
$var wire 1 * En $end
$var wire 3 + W [2:0] $end
$var reg 8 , Y [0:7] $end
$var integer 32 - k [31:0] $end
$upscope $end
$upscope $end
$upscope $end
$enddefinitions $end
#0
$dumpvars
b1000 -
b0 ,
b0 +
0*
b1000 )
b10000000 (
b0 '
1&
b1000000000000000 %
b0 $
b0 #
1"
b1000000000000000 !
$end
#10
b100000000000000 !
b100000000000000 %
b1000000 (
b1000 )
b1000 -
b1 '
b1 +
b1 #
b1 $
#20
b10000000000000 !
b10000000000000 %
b100000 (
b1000 )
b1000 -
b10 '
b10 +
b10 #
b10 $
#30
b1000000000000 !
b1000000000000 %
b10000 (
b1000 )
b1000 -
b11 '
b11 +
b11 #
b11 $
#40
b100000000000 !
b100000000000 %
b1000 (
b1000 )
b1000 -
b100 '
b100 +
b100 #
b100 $
#50
b10000000000 !
b10000000000 %
b100 (
b1000 )
b1000 -
b101 '
b101 +
b101 #
b101 $
#60
b1000000000 !
b1000000000 %
b10 (
b1000 )
b1000 -
b110 '
b110 +
b110 #
b110 $
#70
b100000000 !
b100000000 %
b1 (
b1000 )
b1000 -
b111 '
b111 +
b111 #
b111 $
#80
0&
b0 (
b1000 )
b10000000 !
b10000000 %
b10000000 ,
b1000 -
1*
b0 '
b0 +
b1000 #
b1000 $
#90
b1000 )
b1000000 !
b1000000 %
b1000000 ,
b1000 -
b1 '
b1 +
b1001 #
b1001 $
#100
b1000 )
b100000 !
b100000 %
b100000 ,
b1000 -
b10 '
b10 +
b1010 #
b1010 $
#110
b1000 )
b10000 !
b10000 %
b10000 ,
b1000 -
b11 '
b11 +
b1011 #
b1011 $
#120
b1000 )
b1000 !
b1000 %
b1000 ,
b1000 -
b100 '
b100 +
b1100 #
b1100 $
#130
b1000 )
b100 !
b100 %
b100 ,
b1000 -
b101 '
b101 +
b1101 #
b1101 $
#140
b1000 )
b10 !
b10 %
b10 ,
b1000 -
b110 '
b110 +
b1110 #
b1110 $
#150
b1000 )
b1 !
b1 %
b1 ,
b1000 -
b111 '
b111 +
b1111 #
b1111 $
