Semester_3/DSDL/lab8/q3.v
module q3(W, En, Y);
	input [3:0]W;
	input En;
	output [0:15]Y;
	wire [0:3]en;
	dec2to4 stage0(W[3:2], En, en[0:3]);
	dec2to4 stage1(W[1:0], ~en[0], Y[0:3]);
	dec2to4 stage2(W[1:0], ~en[1], Y[4:7]);
	dec2to4 stage3(W[1:0], ~en[2], Y[8:11]);
	dec2to4 stage4(W[1:0], ~en[3], Y[12:15]);
endmodule

module dec2to4(W, En, Y);
	input [1:0]W;
	input En;
	output [0:3]Y;
	reg [0:3]Y;
	always @(W or En)
	begin
	if(En==0)
		Y=4'b1111;
	else
	begin
	case(W)
		0:Y=4'b0111;
		1:Y=4'b1011;
		2:Y=4'b1101;
		3:Y=4'b1110;
	endcase	
	end
	end
endmodule

Semester_3/DSDL/lab8/q3_tb.v
`timescale 1ns/1ns
`include "q3.v"

module q3_tb();
reg [3:0]W;
reg En;
wire [0:15]Y;
q3 q3(W, En, Y);
initial 
begin

	$dumpfile("q3_tb.vcd");
	$dumpvars(0, q3_tb);

	W=4'b0000;En=1'b1;#10;
	W=4'b0001;En=1'b1;#10;
	W=4'b0010;En=1'b1;#10;
	W=4'b0011;En=1'b1;#10;
	W=4'b0100;En=1'b1;#10;
	W=4'b0101;En=1'b1;#10;
	W=4'b0110;En=1'b1;#10;
	W=4'b0111;En=1'b1;#10;
	W=4'b1000;En=1'b1;#10;
	W=4'b1001;En=1'b1;#10;
	W=4'b1010;En=1'b1;#10;
	W=4'b1011;En=1'b1;#10;
	W=4'b1100;En=1'b1;#10;
	W=4'b1101;En=1'b1;#10;
	W=4'b1110;En=1'b1;#10;
	W=4'b1111;En=1'b1;#10;

	$display("Test Completed");

end 
endmodule

Semester_3/DSDL/lab8/q3_tb.vcd
$date
	Thu Oct 20 10:27:26 2022
$end
$version
	Icarus Verilog
$end
$timescale
	1ns
$end
$scope module q3_tb $end
$var wire 16 ! Y [0:15] $end
$var reg 1 " En $end
$var reg 4 # W [3:0] $end
$scope module q3 $end
$var wire 1 " En $end
$var wire 4 $ W [3:0] $end
$var wire 4 % en [0:3] $end
$var wire 16 & Y [0:15] $end
$scope module stage0 $end
$var wire 1 " En $end
$var wire 2 ' W [1:0] $end
$var reg 4 ( Y [0:3] $end
$upscope $end
$scope module stage1 $end
$var wire 1 ) En $end
$var wire 2 * W [1:0] $end
$var reg 4 + Y [0:3] $end
$upscope $end
$scope module stage2 $end
$var wire 1 , En $end
$var wire 2 - W [1:0] $end
$var reg 4 . Y [0:3] $end
$upscope $end
$scope module stage3 $end
$var wire 1 / En $end
$var wire 2 0 W [1:0] $end
$var reg 4 1 Y [0:3] $end
$upscope $end
$scope module stage4 $end
$var wire 1 2 En $end
$var wire 2 3 W [1:0] $end
$var reg 4 4 Y [0:3] $end
$upscope $end
$upscope $end
$upscope $end
$enddefinitions $end
#0
$dumpvars
b1111 4
b0 3
02
b1111 1
b0 0
0/
b1111 .
b0 -
0,
b111 +
b0 *
1)
b111 (
b0 '
b111111111111111 &
b111 %
b0 $
b0 #
1"
b111111111111111 !
$end
#10
b1011111111111111 !
b1011111111111111 &
b1011 +
b1 *
b1 -
b1 0
b1 3
b1 #
b1 $
#20
b1101111111111111 !
b1101111111111111 &
b1101 +
b10 *
b10 -
b10 0
b10 3
b10 #
b10 $
#30
b1110111111111111 !
b1110111111111111 &
b1110 +
b11 *
b11 -
b11 0
b11 3
b11 #
b11 $
#40
b111 .
1,
0)
b1011 %
b1011 (
b1111011111111111 !
b1111011111111111 &
b1111 +
b1 '
b0 *
b0 -
b0 0
b0 3
b100 #
b100 $
#50
b1111101111111111 !
b1111101111111111 &
b1011 .
b1 *
b1 -
b1 0
b1 3
b101 #
b101 $
#60
b1111110111111111 !
b1111110111111111 &
b1101 .
b10 *
b10 -
b10 0
b10 3
b110 #
b110 $
#70
b1111111011111111 !
b1111111011111111 &
b1110 .
b11 *
b11 -
b11 0
b11 3
b111 #
b111 $
#80
b111 1
1/
0,
b1101 %
b1101 (
b1111111101111111 !
b1111111101111111 &
b1111 .
b10 '
b0 *
b0 -
b0 0
b0 3
b1000 #
b1000 $
#90
b1111111110111111 !
b1111111110111111 &
b1011 1
b1 *
b1 -
b1 0
b1 3
b1001 #
b1001 $
#100
b1111111111011111 !
b1111111111011111 &
b1101 1
b10 *
b10 -
b10 0
b10 3
b1010 #
b1010 $
#110
b1111111111101111 !
b1111111111101111 &
b1110 1
b11 *
b11 -
b11 0
b11 3
b1011 #
b1011 $
#120
b111 4
12
0/
b1110 %
b1110 (
b1111111111110111 !
b1111111111110111 &
b1111 1
b11 '
b0 *
b0 -
b0 0
b0 3
b1100 #
b1100 $
#130
b1111111111111011 !
b1111111111111011 &
b1011 4
b1 *
b1 -
b1 0
b1 3
b1101 #
b1101 $
#140
b1111111111111101 !
b1111111111111101 &
b1101 4
b10 *
b10 -
b10 0
b10 3
b1110 #
b1110 $
#150
b1111111111111110 !
b1111111111111110 &
b1110 4
b11 *
b11 -
b11 0
b11 3
b1111 #
b1111 $
