Semester_3/DSDL/lab8/q5.v
module q5(W, Z, Y);
	input [0:15]W;
	output reg [0:3]Y;
	output reg Z;
	integer k;
	always @(W)
		begin
			Z=0;
			if(W==0)
				Y=0;
			else 
				begin
					for(k=0; k<16; k=k+1)
					begin 
						if(W[k]==1)
							Y=k;
					end
					Z=1;
				end
		end
endmodule

Semester_3/DSDL/lab8/q5_tb.v
`timescale 1ns/1ns
`include "q5.v"

module q5_tb();
reg [0:15]W;
wire [0:3]Y;
wire Z;
q5 q5(W, Z, Y);
initial 
begin

	$dumpfile("q5_tb.vcd");
	$dumpvars(0, q5_tb);

	W=16'b 1000000000000000; #10;
	W=16'b 0100000000000000; #10;
	W=16'b 0010000000000000; #10;
	W=16'b 0001000000000000; #10;
	W=16'b 0000100000000000; #10;
	W=16'b 0000010000000000; #10;
	W=16'b 0000001000000000; #10;
	W=16'b 0000000100000000; #10;
	W=16'b 0000000010000000; #10;
	W=16'b 0000000001000000; #10;
	W=16'b 0000000000100000; #10;
	W=16'b 0000000000010000; #10;
	W=16'b 0000000000001000; #10;
	W=16'b 0000000000000100; #10;
	W=16'b 0000000000000010; #10;
	W=16'b 0000000000000001; #10;


	$display("Test Completed");

end 
endmodule

Semester_3/DSDL/lab8/q5_tb.vcd
$date
	Thu Oct 20 10:58:38 2022
$end
$version
	Icarus Verilog
$end
$timescale
	1ns
$end
$scope module q5_tb $end
$var wire 1 ! Z $end
$var wire 4 " Y [0:3] $end
$var reg 16 # W [0:15] $end
$scope module q5 $end
$var wire 16 $ W [0:15] $end
$var reg 4 % Y [0:3] $end
$var reg 1 ! Z $end
$var integer 32 & k [31:0] $end
$upscope $end
$upscope $end
$enddefinitions $end
#0
$dumpvars
b10000 &
b0 %
b1000000000000000 $
b1000000000000000 #
b0 "
1!
$end
#10
b1 "
b1 %
b10000 &
1!
b100000000000000 #
b100000000000000 $
#20
b10 "
b10 %
b10000 &
1!
b10000000000000 #
b10000000000000 $
#30
b11 "
b11 %
b10000 &
1!
b1000000000000 #
b1000000000000 $
#40
b100 "
b100 %
b10000 &
1!
b100000000000 #
b100000000000 $
#50
b101 "
b101 %
b10000 &
1!
b10000000000 #
b10000000000 $
#60
b110 "
b110 %
b10000 &
1!
b1000000000 #
b1000000000 $
#70
b111 "
b111 %
b10000 &
1!
b100000000 #
b100000000 $
#80
b1000 "
b1000 %
b10000 &
1!
b10000000 #
b10000000 $
#90
b1001 "
b1001 %
b10000 &
1!
b1000000 #
b1000000 $
#100
b1010 "
b1010 %
b10000 &
1!
b100000 #
b100000 $
#110
b1011 "
b1011 %
b10000 &
1!
b10000 #
b10000 $
#120
b1100 "
b1100 %
b10000 &
1!
b1000 #
b1000 $
#130
b1101 "
b1101 %
b10000 &
1!
b100 #
b100 $
#140
b1110 "
b1110 %
b10000 &
1!
b10 #
b10 $
#150
b1111 "
b1111 %
b10000 &
1!
b1 #
b1 $
